autoprep/__init__.py
autoprep/autoprep.py
autoprep/encoder.py
autoprep/nan_handler.py
autoprep/outlier_handler.py
autoprep/scaler.py
autoprep/skew_handler.py
ez_autoprep-0.1.0.dist-info/METADATA
ez_autoprep-0.1.0.dist-info/WHEEL
ez_autoprep-0.1.0.dist-info/top_level.txt
ez_autoprep-0.1.0.dist-info/RECORD
