Metadata-Version: 2.4
Name: ez-autoprep
Version: 0.1.0
Summary: A library for automated data preprocessing
Home-page: https://github.com/hassanrasheed-pydev/AutoPrep
Author: Hassan Rasheed
Author-email: craftycode121@gmail.com
Keywords: preprocessing,data-science,machine-learning,transformers
Classifier: Programming Language :: Python :: 3
Classifier: License :: OSI Approved :: MIT License
Classifier: Operating System :: OS Independent
Requires-Python: >=3.11
Requires-Dist: numpy>=2.4.1
Dynamic: author
Dynamic: author-email
Dynamic: classifier
Dynamic: description
Dynamic: description-content-type
Dynamic: home-page
Dynamic: keywords
Dynamic: requires-dist
Dynamic: requires-python
Dynamic: summary
